berliner/__init__.py
berliner/mist/__init__.py
berliner/mist/_isochrone.py
berliner/mist/_test.py
berliner/mist/_track.py
berliner/mist/bc/__init__.py
berliner/mist/bc/_bc.py
berliner/mist/bc/_test.py
berliner/parsec/__init__.py
berliner/parsec/_deprecated_isochrone.py
berliner/parsec/_deprecated_mist.py
berliner/parsec/_deprecated_track.py
berliner/parsec/_test.py
berliner/parsec/cmd.py
berliner/parsec/isochrone.py
berliner/parsec/isochrone_grid.py
berliner/parsec/parsec_prosenfield.py
berliner/utils/README.md
berliner/utils/__init__.py
berliner/utils/_isochrone_set.py
berliner/utils/_test.py
berliner/utils/_track_set.py
berliner/utils/imf.py
berliner/utils/isochrone_interp.py
berliner/utils/ls.py
berliner/utils/machine.py
berliner/utils/pepsi.py
berliner-0.1.1.dist-info/LICENSE
berliner-0.1.1.dist-info/METADATA
berliner-0.1.1.dist-info/WHEEL
berliner-0.1.1.dist-info/top_level.txt
berliner-0.1.1.dist-info/RECORD
