Metadata-Version: 2.1
Name: berliner
Version: 0.1.1
Summary: Tools for stellar tracks & isochrones.
Home-page: http://github.com/hypergravity/berliner
Author: Bo Zhang
Author-email: bozhang@nao.cas.cn
License: MIT
Platform: UNKNOWN
Classifier: Development Status :: 5 - Production/Stable
Classifier: Intended Audience :: Science/Research
Classifier: License :: OSI Approved :: MIT License
Classifier: Operating System :: OS Independent
Classifier: Programming Language :: Python :: 3.7
Classifier: Topic :: Scientific/Engineering :: Physics
Classifier: Topic :: Scientific/Engineering :: Astronomy
Requires: numpy
Requires: scipy
Requires: emcee
Requires: regli
Requires: joblib
